munch_storage_swift/__about__.py
munch_storage_swift/__init__.py
munch_storage_swift/apps.py
munch_storage_swift-0.1.0.dist-info/DESCRIPTION.rst
munch_storage_swift-0.1.0.dist-info/METADATA
munch_storage_swift-0.1.0.dist-info/RECORD
munch_storage_swift-0.1.0.dist-info/WHEEL
munch_storage_swift-0.1.0.dist-info/metadata.json
munch_storage_swift-0.1.0.dist-info/top_level.txt
