Metadata-Version: 2.0
Name: munch-storage-swift
Version: 0.1.0
Summary: Swift storage backend for munch-core.
Home-page: https://github.com/crunchmail/munch-storageswift
Author: Crunchmail
Author-email: dev@crunchmail.com
License: GNU AGPLv3
Platform: UNKNOWN
Classifier: Framework :: Django
Classifier: Operating System :: OS Independent
Classifier: Programming Language :: Python
Classifier: Programming Language :: Python :: 3
Classifier: Programming Language :: Python :: 3.4
Classifier: Topic :: Internet :: WWW/HTTP
Classifier: Topic :: Internet :: WWW/HTTP :: Dynamic Content
Classifier: License :: OSI Approved :: GNU Affero General Public License v3 or later (AGPLv3+)
Requires-Dist: django-storage-swift (==1.2.12)
Provides-Extra: tests
Requires-Dist: bumpversion (==0.5.3); extra == 'tests'
Requires-Dist: flake8 (==2.5.4); extra == 'tests'
